CHANGES.txt
COPYRIGHT.txt
LICENSE.txt
MANIFEST.in
README.txt
buildout.cfg
setup.py
src/hurry/__init__.py
src/hurry.tinymce.egg-info/PKG-INFO
src/hurry.tinymce.egg-info/SOURCES.txt
src/hurry.tinymce.egg-info/dependency_links.txt
src/hurry.tinymce.egg-info/entry_points.txt
src/hurry.tinymce.egg-info/namespace_packages.txt
src/hurry.tinymce.egg-info/not-zip-safe
src/hurry.tinymce.egg-info/requires.txt
src/hurry.tinymce.egg-info/top_level.txt
src/hurry/tinymce/__init__.py
src/hurry/tinymce/basic.txt
src/hurry/tinymce/configure.zcml
src/hurry/tinymce/download.py
src/hurry/tinymce/prepare.py
src/hurry/tinymce/tests.py
src/hurry/tinymce/tinymce.py
src/hurry/tinymce/tinymce-build/license.txt
src/hurry/tinymce/tinymce-build/tiny_mce.js
src/hurry/tinymce/tinymce-build/tiny_mce_popup.js
src/hurry/tinymce/tinymce-build/tiny_mce_src.js
src/hurry/tinymce/tinymce-build/langs/de.js
src/hurry/tinymce/tinymce-build/langs/en.js
src/hurry/tinymce/tinymce-build/plugins/advhr/editor_plugin.js
src/hurry/tinymce/tinymce-build/plugins/advhr/editor_plugin_src.js
src/hurry/tinymce/tinymce-build/plugins/advhr/rule.htm
src/hurry/tinymce/tinymce-build/plugins/advhr/css/advhr.css
src/hurry/tinymce/tinymce-build/plugins/advhr/js/rule.js
src/hurry/tinymce/tinymce-build/plugins/advhr/langs/de_dlg.js
src/hurry/tinymce/tinymce-build/plugins/advhr/langs/en_dlg.js
src/hurry/tinymce/tinymce-build/plugins/advimage/editor_plugin.js
src/hurry/tinymce/tinymce-build/plugins/advimage/editor_plugin_src.js
src/hurry/tinymce/tinymce-build/plugins/advimage/image.htm
src/hurry/tinymce/tinymce-build/plugins/advimage/css/advimage.css
src/hurry/tinymce/tinymce-build/plugins/advimage/img/sample.gif
src/hurry/tinymce/tinymce-build/plugins/advimage/js/image.js
src/hurry/tinymce/tinymce-build/plugins/advimage/langs/de_dlg.js
src/hurry/tinymce/tinymce-build/plugins/advimage/langs/en_dlg.js
src/hurry/tinymce/tinymce-build/plugins/advlink/editor_plugin.js
src/hurry/tinymce/tinymce-build/plugins/advlink/editor_plugin_src.js
src/hurry/tinymce/tinymce-build/plugins/advlink/link.htm
src/hurry/tinymce/tinymce-build/plugins/advlink/css/advlink.css
src/hurry/tinymce/tinymce-build/plugins/advlink/js/advlink.js
src/hurry/tinymce/tinymce-build/plugins/advlink/langs/de_dlg.js
src/hurry/tinymce/tinymce-build/plugins/advlink/langs/en_dlg.js
