Metadata-Version: 1.0
Name: hurry.tinymce
Version: 3.3.9.4
Summary: TinyMCE for hurry.resource.
Home-page: UNKNOWN
Author: Martijn Faassen
Author-email: faassen@startifact.com
License: ZPL 2.1
Platform: UNKNOWN
